darkmappy/__init__.py
darkmappy/estimators.py
darkmappy/forward_models.py
darkmappy/logs.py
darkmappy/noise_simulations.py
darkmappy/solvers.py
darkmappy/validation.py
darkmappy/wavelet_wrappers.py
darkmappy-0.1.0.dist-info/LICENSE.txt
darkmappy-0.1.0.dist-info/METADATA
darkmappy-0.1.0.dist-info/WHEEL
darkmappy-0.1.0.dist-info/top_level.txt
darkmappy-0.1.0.dist-info/RECORD
