Metadata-Version: 2.1
Name: darkmappy
Version: 0.1.0
Summary: Scalable hybrid Bayesian dark-matter reconstruction algorithms
Home-page: https://github.com/astro-informatics/DarkMappy
Author: Matthew A. Price, Jason D. McEwen & Contributors
Author-email: m.price.17@ucl.ac.uk
License: GNU General Public License v3 (GPLv3)
Platform: UNKNOWN
Classifier: Programming Language :: Python :: 3.6
Classifier: Programming Language :: Python :: 3.7
Classifier: Programming Language :: Python :: 3.8
Classifier: Operating System :: OS Independent
Classifier: Intended Audience :: Developers
Classifier: Intended Audience :: Science/Research
License-File: LICENSE.txt
Requires-Dist: numpy
Requires-Dist: colorlog
Requires-Dist: pyyaml
Requires-Dist: pys2let
Requires-Dist: pyssht
Requires-Dist: optimusprimal
